setup.py
SlowTests.egg-info/PKG-INFO
SlowTests.egg-info/SOURCES.txt
SlowTests.egg-info/dependency_links.txt
SlowTests.egg-info/entry_points.txt
SlowTests.egg-info/requires.txt
SlowTests.egg-info/top_level.txt
slow_tests/__init__.py