Metadata-Version: 1.0
Name: SlowTests
Version: 0.0.5
Summary: Plugin for noset that identifies and prints your slowest tests
Home-page: https://github.com/yellow-beard/slow_tests
Author: Yellowbeard
Author-email: artbasher@gmail.com
License: MIT License
Platform: UNKNOWN
